pymuscle/__init__.py
pymuscle/__version__.py
pymuscle/hill_type.py
pymuscle/model.py
pymuscle/muscle.py
pymuscle/potvin_fuglevand_2017_motor_neuron_pool.py
pymuscle/potvin_fuglevand_2017_muscle_fibers.py
pymuscle/pymuscle_fibers.py
pymuscle/vis/__init__.py
pymuscle/vis/potvin_charts.py
pymuscle-0.1.2.dist-info/METADATA
pymuscle-0.1.2.dist-info/RECORD
pymuscle-0.1.2.dist-info/WHEEL
pymuscle-0.1.2.dist-info/top_level.txt
