Metadata-Version: 2.1
Name: pymuscle
Version: 0.1.2
Summary: A motor unit based model of skeletal muscle and fatigue
Home-page: https://github.com/iandanforth/pymuscle
Author: Ian Danforth
Author-email: iandanforth@gmail.com
License: MIT + No Military Use
Platform: UNKNOWN
Classifier: Programming Language :: Python
Classifier: Programming Language :: Python :: 3
Classifier: Programming Language :: Python :: 3.6
Classifier: Programming Language :: Python :: Implementation :: CPython
Classifier: Programming Language :: Python :: Implementation :: PyPy
Requires-Python: >=3.6.0
Requires-Dist: numpy
Requires-Dist: plotly
Requires-Dist: colorlover
